torchfun/__init__.py
torchfun/torchfun.py
torchure-0.0.14.dist-info/METADATA
torchure-0.0.14.dist-info/RECORD
torchure-0.0.14.dist-info/WHEEL
torchure-0.0.14.dist-info/top_level.txt
