Metadata-Version: 2.1
Name: torchure
Version: 0.0.14
Summary: A collection of small functions that supplements torch functionality
Home-page: https://github.com/sorenchiron/torchfun
Author: CHEN Si Yu
Author-email: sychen@zju.edu.cn
License: UNKNOWN
Platform: UNKNOWN
Classifier: Programming Language :: Python
Classifier: License :: OSI Approved :: MIT License
Classifier: Operating System :: OS Independent
Classifier: Topic :: Scientific/Engineering :: Artificial Intelligence
Classifier: License :: OSI Approved :: MIT License
Requires-Dist: numpy
Requires-Dist: torch
Requires-Dist: torchvision
Requires-Dist: matplotlib
